[
  {
    "law_name": "VTS",
    "article_ref": "Art. 175 Abs. 1, 178 Abs. 2 und 214 Abs. 1 VTS",
    "law_text": "Mangelhafter Zustand des Reifens pro Rad",
    "fine_chf": 20,
    "keywords": [
      "Reifen",
      "Zustand",
      "mangelhaft",
      "VTS",
      "Rad",
      "tire",
      "equipment"
    ],
    "road_category": "equipment",
    "applies_to": [
      "Fahrzeug"
    ],
    "conditions": "pro Rad",
    "notes": "Relates to item 704.",
    "source": {
      "page": 24,
      "line_hint": "704."
    }
  },
  {
    "law_name": "VRV",
    "article_ref": "Art. 3a Abs. 1 VRV",
    "law_text": "Nichttragen der Sicherheitsgurten durch die Mitfahrerin oder den Mitfahrer",
    "fine_chf": 60,
    "keywords": [
      "Sicherheitsgurten",
      "Gurtpflicht",
      "Mitfahrer",
      "Passagier",
      "safety belt",
      "passenger"
    ],
    "road_category": "other-road",
    "applies_to": [
      "Mitfahrer",
      "Passagier"
    ],
    "conditions": null,
    "notes": "Section 800.1: Non-use of seat belts by passengers.",
    "source": {
      "page": 24,
      "line_hint": "800.1"
    }
  },
  {
    "law_name": "VRV",
    "article_ref": "Art. 3b VRV",
    "law_text": "Nichttragen des Schutzhelmes durch Mitfahrerin oder Mitfahrer auf Motorrädern, Leicht-, Klein- und dreirädrigen Motorfahrzeugen",
    "fine_chf": 60,
    "keywords": [
      "Schutzhelm",
      "Helmpflicht",
      "Mitfahrer",
      "Motorrad",
      "helmet",
      "passenger"
    ],
    "road_category": "equipment",
    "applies_to": [
      "Mitfahrer",
      "Motorräder"
    ],
    "conditions": null,
    "notes": "Section 800.2: Non-use of helmet by passengers on motorcycles/three-wheeled vehicles.",
    "source": {
      "page": 24,
      "line_hint": "800.2"
    }
  },
  {
    "law_name": "VRV",
    "article_ref": "Art. 71 Abs. 1 VRV",
    "law_text": "Stossen eines Fahrzeugs oder Gegenstandes durch eine Mitfahrerin oder einen Mitfahrer",
    "fine_chf": 20,
    "keywords": [
      "Stossen",
      "Fahrzeug",
      "Gegenstand",
      "Mitfahrer",
      "push",
      "object",
      "passenger"
    ],
    "road_category": "other-road",
    "applies_to": [
      "Mitfahrer"
    ],
    "conditions": null,
    "notes": "Section 801.1: Pushing a vehicle or object by a passenger (likely prohibited behavior while moving/in traffic).",
    "source": {
      "page": 24,
      "line_hint": "801.1"
    }
  },
  {
    "law_name": "VRV",
    "article_ref": "Art. 71 Abs. 1 VRV",
    "law_text": "Ziehen eines Fahrzeugs oder Gegenstandes durch eine Mitfahrerin oder einen Mitfahrer",
    "fine_chf": 20,
    "keywords": [
      "Ziehen",
      "Fahrzeug",
      "Gegenstand",
      "Mitfahrer",
      "pull",
      "object",
      "passenger"
    ],
    "road_category": "other-road",
    "applies_to": [
      "Mitfahrer"
    ],
    "conditions": null,
    "notes": "Section 801.2: Pulling a vehicle or object by a passenger.",
    "source": {
      "page": 24,
      "line_hint": "801.2"
    }
  },
  {
    "law_name": "VRV",
    "article_ref": "Art. 71 Abs. 1 VRV",
    "law_text": "Schleppen eines Fahrzeugs oder Gegenstandes durch eine Mitfahrerin oder einen Mitfahrer",
    "fine_chf": 20,
    "keywords": [
      "Schleppen",
      "Fahrzeug",
      "Gegenstand",
      "Mitfahrer",
      "tow",
      "object",
      "passenger"
    ],
    "road_category": "other-road",
    "applies_to": [
      "Mitfahrer"
    ],
    "conditions": null,
    "notes": "Section 801.3: Towing/dragging a vehicle or object by a passenger.",
    "source": {
      "page": 24,
      "line_hint": "801.3"
    }
  },
  {
    "law_name": "SVG",
    "article_ref": "Art. 49 Abs. 1 SVG",
    "law_text": "Nichtbenützen des Trottoirs",
    "fine_chf": 10,
    "keywords": [
      "Trottoir",
      "Gehweg",
      "Nichtbenützen",
      "Fussgänger",
      "sidewalk",
      "pedestrian"
    ],
    "road_category": "pedestrian",
    "applies_to": [
      "Fussgänger"
    ],
    "conditions": null,
    "notes": "Failure to use the sidewalk when available.",
    "source": {
      "page": 24,
      "line_hint": "900."
    }
  },
  {
    "law_name": "VRV",
    "article_ref": "Art. 47 Abs. 1 und Art. 50a Abs. 1 VRV",
    "law_text": "Nichtbenützen des Fussgängerstreifens, sofern er weniger als 50 m entfernt ist",
    "fine_chf": 10,
    "keywords": [
      "Fussgängerstreifen",
      "Zebrastreifen",
      "Nichtbenützen",
      "50m",
      "pedestrian crossing"
    ],
    "road_category": "pedestrian",
    "applies_to": [
      "Fussgänger"
    ],
    "conditions": "sofern weniger als 50 m entfernt",
    "notes": null,
    "source": {
      "page": 24,
      "line_hint": "901.1"
    }
  },
  {
    "law_name": "VRV",
    "article_ref": "Art. 47 Abs. 1 und Art. 50a Abs. 1 VRV",
    "law_text": "Nichtbenützen einer Überführung, sofern sie weniger als 50 m entfernt ist",
    "fine_chf": 10,
    "keywords": [
      "Überführung",
      "Fussgängerbrücke",
      "Nichtbenützen",
      "50m",
      "pedestrian overpass"
    ],
    "road_category": "pedestrian",
    "applies_to": [
      "Fussgänger"
    ],
    "conditions": "sofern weniger als 50 m entfernt",
    "notes": null,
    "source": {
      "page": 24,
      "line_hint": "901.2"
    }
  },
  {
    "law_name": "VRV",
    "article_ref": "Art. 47 Abs. 1 und Art. 50a Abs. 1 VRV",
    "law_text": "Nichtbenützen einer Unterführung, sofern sie weniger als 50 m entfernt ist",
    "fine_chf": 10,
    "keywords": [
      "Unterführung",
      "Fussgängertunnel",
      "Nichtbenützen",
      "50m",
      "pedestrian underpass"
    ],
    "road_category": "pedestrian",
    "applies_to": [
      "Fussgänger"
    ],
    "conditions": "sofern weniger als 50 m entfernt",
    "notes": null,
    "source": {
      "page": 24,
      "line_hint": "901.3"
    }
  },
  {
    "law_name": "SSV",
    "article_ref": "2.15; Art. 19 Abs. 3 SSV",
    "law_text": "Nichtbeachten des Signals «Verbot für Fussgänger» (2.15)",
    "fine_chf": 20,
    "keywords": [
      "Verbot",
      "Fussgänger",
      "Signal",
      "Nichtbeachten",
      "restriction",
      "pedestrian",
      "sign"
    ],
    "road_category": "signaling",
    "applies_to": [
      "Fussgänger"
    ],
    "conditions": null,
    "notes": null,
    "source": {
      "page": 24,
      "line_hint": "902.1"
    }
  },
  {
    "law_name": "SSV",
    "article_ref": "2.61; Art. 33 Abs. 2 SSV",
    "law_text": "Nichtbeachten des Signals «Fussweg» (2.61)",
    "fine_chf": 10,
    "keywords": [
      "Fussweg",
      "Signal",
      "Nichtbeachten",
      "pedestrian path",
      "sign"
    ],
    "road_category": "signaling",
    "applies_to": [
      "Fussgänger"
    ],
    "conditions": null,
    "notes": "Non-compliance with the dedicated pedestrian path sign.",
    "source": {
      "page": 24,
      "line_hint": "902.2"
    }
  },
  {
    "law_name": "SVG",
    "article_ref": "Art. 27 Abs. 1 SVG, Art. 50a Abs. 1 VRV und Art. 68 SSV",
    "law_text": "Nichtbeachten eines Lichtsignals",
    "fine_chf": 20,
    "keywords": [
      "Lichtsignal",
      "Fussgänger",
      "Signal",
      "Nichtbeachten",
      "traffic light",
      "pedestrian"
    ],
    "road_category": "signaling",
    "applies_to": [
      "Fussgänger",
      "Benutzer fahrzeugähnlicher Geräte"
    ],
    "conditions": null,
    "notes": "Running a red light (as a pedestrian/user of mobility device).",
    "source": {
      "page": 24,
      "line_hint": "903.1"
    }
  },
  {
    "law_name": "SVG",
    "article_ref": "3.20; 3.21; Art. 28 SVG, Art. 68 Abs. 1bis und 93 Abs. 2 SSV und Art. 50a Abs. 1 VRV",
    "law_text": "Nichtbeachten eines «Wechselblinklichtsignals» (3.20) oder eines «Einfachen Blinklichtsignals» (3.21)",
    "fine_chf": 20,
    "keywords": [
      "Blinklichtsignal",
      "Wechselblinklicht",
      "Signal",
      "Bahnübergang",
      "warning light",
      "level crossing"
    ],
    "road_category": "signaling",
    "applies_to": [
      "Fussgänger",
      "Benutzer fahrzeugähnlicher Geräte"
    ],
    "conditions": null,
    "notes": "Ignoring flashing warning lights (e.g., at level crossings).",
    "source": {
      "page": 24,
      "line_hint": "903.2"
    }
  },
  {
    "law_name": "SVG",
    "article_ref": "Art. 43 Abs. 3 SVG, Art. 36 Abs. 3 und 50a Abs. 1 VRV",
    "law_text": "Betreten von Autobahnen",
    "fine_chf": 20,
    "keywords": [
      "Autobahn",
      "Betreten",
      "Fussgänger",
      "Verbot",
      "Motorway",
      "access",
      "forbidden"
    ],
    "road_category": "pedestrian",
    "applies_to": [
      "Fussgänger",
      "Benutzer fahrzeugähnlicher Geräte"
    ],
    "conditions": null,
    "notes": "Entering or walking on motorways (which is generally restricted to motorized traffic).",
    "source": {
      "page": 24,
      "line_hint": "904.1"
    }
  }
]